stift/__init__.py
stift/compiles.py
stift/exceptions.py
stift/parser.py
stift/stift.py
stift/functions/__init__.py
stift/functions/base.py
stift/functions/date.py
stift/functions/info.py
stift/functions/logical.py
stift/functions/math.py
stift/functions/operator.py
stift/functions/text.py
stift-0.3.0.dist-info/LICENSE
stift-0.3.0.dist-info/METADATA
stift-0.3.0.dist-info/WHEEL
stift-0.3.0.dist-info/top_level.txt
stift-0.3.0.dist-info/RECORD
