Metadata-Version: 2.1
Name: stift
Version: 0.3.0
Summary: A package to implement spreadsheet-style functions in a safe way
Home-page: https://github.com/tgross35/stift
Author: Trevor Gross
Author-email: t.gross35@gmail.com
License: UNKNOWN
Platform: UNKNOWN
Classifier: Programming Language :: Python :: 3
Classifier: License :: OSI Approved :: MIT License
Classifier: Operating System :: OS Independent
Requires-Python: >=3.8
License-File: LICENSE
